extrpc-plugin-example/my_extrpc_plugin/ExampleCommand.py
extrpc-plugin-example/my_extrpc_plugin/__init__.py
extrpc-plugin-example/my_extrpc_plugin/test_example.py
neopython_ext_rpc_server/ExtRpcCommand.py
neopython_ext_rpc_server/ExtRpcServer.py
neopython_ext_rpc_server/ExtRpcTestCase.py
neopython_ext_rpc_server/__init__.py
neopython_extended_rpc_server-0.1.0.dist-info/LICENSE
neopython_extended_rpc_server-0.1.0.dist-info/METADATA
neopython_extended_rpc_server-0.1.0.dist-info/WHEEL
neopython_extended_rpc_server-0.1.0.dist-info/top_level.txt
neopython_extended_rpc_server-0.1.0.dist-info/RECORD
