Metadata-Version: 2.1
Name: neopython-extended-rpc-server
Version: 0.1.0
Summary: A neo-python RPC Server with plugable commands.
Home-page: https://github.com/ixje/neopython-extended-rpc-server/
Author: Erik van den Brink
Author-email: erik@cityofzion.io
License: MIT License
Platform: UNKNOWN
Classifier: Intended Audience :: Developers
Classifier: License :: OSI Approved :: MIT License
Classifier: Operating System :: OS Independent
Classifier: Programming Language :: Python
Classifier: Programming Language :: Python :: 3
Classifier: Programming Language :: Python :: 3.6
Classifier: Programming Language :: Python :: 3.7
Requires-Dist: neo-python
